snpsnip/__init__.py
snpsnip/__main__.py
snpsnip/_version.py
snpsnip/generate_example.py
snpsnip/templates/index.html
snpsnip-0.1.0.dist-info/licenses/LICENSE
snpsnip-0.1.0.dist-info/METADATA
snpsnip-0.1.0.dist-info/WHEEL
snpsnip-0.1.0.dist-info/entry_points.txt
snpsnip-0.1.0.dist-info/top_level.txt
snpsnip-0.1.0.dist-info/RECORD
