Metadata-Version: 2.4
Name: snpsnip
Version: 0.1.0
Summary: An interactive VCF filtering tool
License: MIT
Project-URL: Homepage, https://github.com/gekkonid/snpsnip
Project-URL: Bug Tracker, https://github.com/gekkonid/snpsnip/issues
Classifier: Programming Language :: Python :: 3
Classifier: License :: OSI Approved :: MIT License
Classifier: Operating System :: OS Independent
Classifier: Topic :: Scientific/Engineering :: Bio-Informatics
Requires-Python: >=3.8
License-File: LICENSE
Requires-Dist: flask>=2.0.0
Requires-Dist: waitress>=2.0.0
Requires-Dist: numpy>=1.20.0
Requires-Dist: pandas>=1.3.0
Requires-Dist: scikit-learn>=1.0.0
Requires-Dist: tqdm>=4.0.0
Dynamic: license-file
